{
  "servers": [
    {
      "name": "Jerrod Volkman",
      "email": "Bianka.Jast@yahoo.com",
      "password": "jEnJcDu9En8GuNV",
      "restaurant_id": 17
    },
    {
      "name": "Lukas Fisher",
      "email": "Arthur46@gmail.com",
      "password": "Yf7ggpO71tkzvox",
      "restaurant_id": 21
    },
    {
      "name": "Jalen Kuvalis",
      "email": "Cathy.Hyatt96@hotmail.com",
      "password": "m6pstbbAaEECgFQ",
      "restaurant_id": 17
    },
    {
      "name": "Floy Ledner",
      "email": "Ned_Ruecker18@yahoo.com",
      "password": "guNNOBxQcbmcMZL",
      "restaurant_id": 11
    },
    {
      "name": "Willard Cummerata",
      "email": "Colleen.Jacobi50@gmail.com",
      "password": "SsdU_oWrvCuqcwQ",
      "restaurant_id": 22
    },
    {
      "name": "Cassandra Treutel",
      "email": "Kory_Kuphal@gmail.com",
      "password": "jcV76ErcPy0oO1V",
      "restaurant_id": 3
    },
    {
      "name": "Antonette McClure",
      "email": "Elisha.Aufderhar@gmail.com",
      "password": "sa7lwRGdKdz1uR2",
      "restaurant_id": 21
    },
    {
      "name": "Vida Johnson",
      "email": "Marlene.Daugherty86@gmail.com",
      "password": "mo6LHv3ID1RWxDf",
      "restaurant_id": 19
    },
    {
      "name": "Seamus Bartoletti",
      "email": "Jamel.Gutmann63@hotmail.com",
      "password": "SvdQeaVSL5MTVLu",
      "restaurant_id": 12
    },
    {
      "name": "Landen O'Connell",
      "email": "Ana.Auer@gmail.com",
      "password": "485Utf6WtcCpNVk",
      "restaurant_id": 14
    },
    {
      "name": "Ike Toy",
      "email": "Felicia16@hotmail.com",
      "password": "THHvxkl8FWJi2rY",
      "restaurant_id": 1
    },
    {
      "name": "Alexie Hermiston",
      "email": "Yessenia_Ryan29@yahoo.com",
      "password": "Y8Fuj1IgBpg1XTD",
      "restaurant_id": 24
    },
    {
      "name": "Abbey Swift",
      "email": "Leta.Kuhic@hotmail.com",
      "password": "yz3ZhdNgV6DgzCT",
      "restaurant_id": 23
    },
    {
      "name": "Dahlia Gleichner",
      "email": "Toy43@hotmail.com",
      "password": "Lf4oX8mEAlEQPiu",
      "restaurant_id": 13
    },
    {
      "name": "Olen Wiza",
      "email": "Hayley.Feil@gmail.com",
      "password": "03kmkbhUChyHC7K",
      "restaurant_id": 9
    },
    {
      "name": "Clotilde Pagac",
      "email": "Gilberto57@yahoo.com",
      "password": "TagCOdR2X0919qc",
      "restaurant_id": 9
    },
    {
      "name": "Wellington Gutmann",
      "email": "Lamont.Lueilwitz84@yahoo.com",
      "password": "4BSwjxRqsf_T8n0",
      "restaurant_id": 26
    },
    {
      "name": "Geovanny Jenkins",
      "email": "Jerod.Schuster11@hotmail.com",
      "password": "x508jetBcumYd86",
      "restaurant_id": 24
    },
    {
      "name": "Jewell Roob",
      "email": "Jerel60@hotmail.com",
      "password": "oSCXVqt0leInvSS",
      "restaurant_id": 29
    },
    {
      "name": "Gerald Davis",
      "email": "Karolann11@hotmail.com",
      "password": "dHQ9XgjRXL4FkdR",
      "restaurant_id": 10
    },
    {
      "name": "Jewel Armstrong",
      "email": "Gwen_Jast@gmail.com",
      "password": "7jpmVjl_JNTwwPr",
      "restaurant_id": 8
    },
    {
      "name": "Rogers Skiles",
      "email": "Trace.Schimmel@yahoo.com",
      "password": "T_zjxRZa3WPlZJI",
      "restaurant_id": 24
    },
    {
      "name": "Alva Wolff",
      "email": "Orrin_Quigley91@yahoo.com",
      "password": "CpnADae63orM3AI",
      "restaurant_id": 23
    },
    {
      "name": "Claud Abernathy",
      "email": "Anais44@gmail.com",
      "password": "uLORhpJPwZn5lVH",
      "restaurant_id": 26
    },
    {
      "name": "Xavier Goldner",
      "email": "Nella41@gmail.com",
      "password": "osjm_BNhrV6rqrF",
      "restaurant_id": 29
    },
    {
      "name": "Jewell Johnson",
      "email": "Watson_Paucek@yahoo.com",
      "password": "BHulPwNOe8dJmPV",
      "restaurant_id": 22
    },
    {
      "name": "Destin Armstrong",
      "email": "Guido37@yahoo.com",
      "password": "rJ6GWrZkFW0Ue6t",
      "restaurant_id": 3
    },
    {
      "name": "Aidan Maggio",
      "email": "Juwan_Parisian85@yahoo.com",
      "password": "lhEYlMYyWSst96D",
      "restaurant_id": 22
    },
    {
      "name": "Jessika Ziemann",
      "email": "Devan.Batz38@yahoo.com",
      "password": "g0hffSComgQTtxu",
      "restaurant_id": 9
    },
    {
      "name": "Stewart Wehner",
      "email": "Brannon_Beer29@hotmail.com",
      "password": "X_4FAjmA30g5j7q",
      "restaurant_id": 6
    },
    {
      "name": "Howard Ledner",
      "email": "Howell93@gmail.com",
      "password": "GZBF6VwnYeKSBFJ",
      "restaurant_id": 2
    },
    {
      "name": "Eden Schimmel",
      "email": "Laisha.Pfeffer@hotmail.com",
      "password": "yoGLV2UfboMO8sw",
      "restaurant_id": 14
    },
    {
      "name": "Zelma Kessler",
      "email": "Gregoria51@gmail.com",
      "password": "u5Kzv0ftUZC81vS",
      "restaurant_id": 13
    },
    {
      "name": "Megane Borer",
      "email": "Dorcas37@hotmail.com",
      "password": "8D27d2Hj_gWMOFS",
      "restaurant_id": 4
    },
    {
      "name": "Lila Spinka",
      "email": "Faustino_OReilly@yahoo.com",
      "password": "MmB8SCdT7vvUYNH",
      "restaurant_id": 12
    },
    {
      "name": "Issac Renner",
      "email": "Angelita.Stracke@hotmail.com",
      "password": "wrdKGmtrDuweStJ",
      "restaurant_id": 18
    },
    {
      "name": "Jaron Walter",
      "email": "Virgil93@yahoo.com",
      "password": "VHn_GWGm0imZ1uI",
      "restaurant_id": 19
    },
    {
      "name": "Daisy Brekke",
      "email": "Rollin_Kris69@gmail.com",
      "password": "GSZsSoQBPT4Gpvh",
      "restaurant_id": 10
    },
    {
      "name": "Chloe Friesen",
      "email": "Margarita.Hudson@yahoo.com",
      "password": "TFAVY9mpn2Eofmh",
      "restaurant_id": 6
    },
    {
      "name": "Francesca Reinger",
      "email": "Karine_Little@gmail.com",
      "password": "w5ws34vqI4zBu4i",
      "restaurant_id": 20
    },
    {
      "name": "Leone Leannon",
      "email": "Rebecca_Bergstrom@gmail.com",
      "password": "7nseMbkHMbF_713",
      "restaurant_id": 15
    },
    {
      "name": "Wyman Kunze",
      "email": "Columbus.Cassin95@hotmail.com",
      "password": "N766gOmkzmZU7zB",
      "restaurant_id": 8
    },
    {
      "name": "Eveline Schmidt",
      "email": "Lauretta.Shanahan62@yahoo.com",
      "password": "DdfGww21y2050hp",
      "restaurant_id": 23
    },
    {
      "name": "Linnie Russel",
      "email": "Helena.Boyle@yahoo.com",
      "password": "nxrsz80qTaSSYul",
      "restaurant_id": 18
    },
    {
      "name": "Aylin Kutch",
      "email": "Stefan32@hotmail.com",
      "password": "dfK6gsJK_1fWwJX",
      "restaurant_id": 7
    },
    {
      "name": "Kelli Maggio",
      "email": "Lucio4@yahoo.com",
      "password": "Y22L79rUl5dZq1v",
      "restaurant_id": 25
    },
    {
      "name": "Marta Smith",
      "email": "Moises_Collier16@gmail.com",
      "password": "PRghOhlTqvBRGkW",
      "restaurant_id": 12
    },
    {
      "name": "Kelley Krajcik",
      "email": "Kristoffer_Hudson@hotmail.com",
      "password": "vlycwS4WtpKsLH_",
      "restaurant_id": 11
    },
    {
      "name": "Dante O'Kon",
      "email": "Mariam.Donnelly95@hotmail.com",
      "password": "luLhTL48WzhdGOK",
      "restaurant_id": 22
    },
    {
      "name": "Luna Jenkins",
      "email": "Eleanora.Wisoky@hotmail.com",
      "password": "lY2DkkLxgLYyy2T",
      "restaurant_id": 29
    },
    {
      "name": "Elnora Lockman",
      "email": "Rosina92@yahoo.com",
      "password": "c7iaF5dB8P7EzWG",
      "restaurant_id": 1
    },
    {
      "name": "Kristoffer Greenholt",
      "email": "Isadore55@hotmail.com",
      "password": "5ePaE60yAveK3j9",
      "restaurant_id": 10
    },
    {
      "name": "Sydney Runolfsson",
      "email": "Deshawn_OConnell@gmail.com",
      "password": "josouoyzgGotS0w",
      "restaurant_id": 20
    },
    {
      "name": "Lessie Sporer",
      "email": "Dortha_Howell@gmail.com",
      "password": "zyaEZ_wwQfeboH0",
      "restaurant_id": 30
    },
    {
      "name": "Adelia Batz",
      "email": "Jakayla71@yahoo.com",
      "password": "qB5f13QMtkkJUTi",
      "restaurant_id": 12
    },
    {
      "name": "Friedrich Walter",
      "email": "Summer_Yost@gmail.com",
      "password": "TiIUz2QGoW0Zeyd",
      "restaurant_id": 19
    },
    {
      "name": "Ewell Dickens",
      "email": "Horacio90@yahoo.com",
      "password": "QXDq3lsTUzoitM3",
      "restaurant_id": 26
    },
    {
      "name": "Shea Wilkinson",
      "email": "Josiane.Hessel@hotmail.com",
      "password": "wnCQaybHzvvRuwY",
      "restaurant_id": 19
    },
    {
      "name": "Gussie Ferry",
      "email": "Autumn.Lesch@yahoo.com",
      "password": "UoqHrDgEVTo8a7R",
      "restaurant_id": 24
    },
    {
      "name": "Edwin Ritchie",
      "email": "Obie70@hotmail.com",
      "password": "vSJdZr9ucrCCkTC",
      "restaurant_id": 8
    },
    {
      "name": "Blaze Berge",
      "email": "Owen.Greenholt71@gmail.com",
      "password": "xBRwBgG2mPYnN6E",
      "restaurant_id": 6
    },
    {
      "name": "Lamar Murazik",
      "email": "Ambrose.Abbott6@hotmail.com",
      "password": "f_NAcwwB8A208S7",
      "restaurant_id": 25
    },
    {
      "name": "Madeline Donnelly",
      "email": "Frederic.Howe@hotmail.com",
      "password": "Ppw8p1He0rhAnV7",
      "restaurant_id": 11
    },
    {
      "name": "Tony Ledner",
      "email": "Floy34@yahoo.com",
      "password": "zibTaKuuUgNAc3f",
      "restaurant_id": 23
    },
    {
      "name": "Horace Labadie",
      "email": "Mallie_Halvorson74@gmail.com",
      "password": "i5fI3CKkcmuf4su",
      "restaurant_id": 15
    },
    {
      "name": "Hailey Olson",
      "email": "Connor.Kreiger2@gmail.com",
      "password": "2Q8BVl6nlOhpqcG",
      "restaurant_id": 17
    },
    {
      "name": "Edna Kub",
      "email": "Nestor76@yahoo.com",
      "password": "LP9NbZh6NaN8cHp",
      "restaurant_id": 6
    },
    {
      "name": "Myrtice Hodkiewicz",
      "email": "Myrtis.Kemmer@yahoo.com",
      "password": "NDDZ3YIZ_ybA5Ks",
      "restaurant_id": 9
    },
    {
      "name": "Amara Rohan",
      "email": "Vladimir.Nolan40@yahoo.com",
      "password": "vNgTQQvKyVnEEHw",
      "restaurant_id": 22
    },
    {
      "name": "Sienna Collins",
      "email": "Katlyn.Rohan@gmail.com",
      "password": "GWH7aZtdm9K6SAZ",
      "restaurant_id": 17
    },
    {
      "name": "Alfred Kozey",
      "email": "Mireille_Johns28@gmail.com",
      "password": "y5eI0gOA5YY9yNz",
      "restaurant_id": 8
    },
    {
      "name": "Kelsi Kihn",
      "email": "Alberto_Adams@gmail.com",
      "password": "sE30KprLMKXTmDv",
      "restaurant_id": 18
    },
    {
      "name": "Torrey Monahan",
      "email": "Avis72@yahoo.com",
      "password": "cqISusk6p2SfujI",
      "restaurant_id": 7
    },
    {
      "name": "Kevon Goodwin",
      "email": "Maverick_Gorczany@yahoo.com",
      "password": "JpdhEFhUdu2UkEn",
      "restaurant_id": 27
    },
    {
      "name": "Coleman Kirlin",
      "email": "Jazmin.Kling@hotmail.com",
      "password": "QrnfMYCjqpEyNqb",
      "restaurant_id": 30
    },
    {
      "name": "Myrl Hermiston",
      "email": "Charles.Denesik@yahoo.com",
      "password": "bfgqpIAAMDww7ZA",
      "restaurant_id": 12
    },
    {
      "name": "Al Parker",
      "email": "Lucius.Mann@gmail.com",
      "password": "DoR8XgLXHe0Cg9C",
      "restaurant_id": 14
    },
    {
      "name": "Minnie O'Kon",
      "email": "Lottie_Greenholt@yahoo.com",
      "password": "zqiHGvq4pel95mC",
      "restaurant_id": 14
    },
    {
      "name": "Cary Weissnat",
      "email": "Golden.Osinski@yahoo.com",
      "password": "J99MfgOpX5upi8J",
      "restaurant_id": 8
    },
    {
      "name": "Jeramy Cummerata",
      "email": "Dennis_Kessler70@hotmail.com",
      "password": "ZiYbtcfZrVCZ5IW",
      "restaurant_id": 29
    },
    {
      "name": "Kolby Kunde",
      "email": "Kara.Johns89@hotmail.com",
      "password": "dtP9eweRPQY5qN2",
      "restaurant_id": 7
    },
    {
      "name": "Jovany Greenfelder",
      "email": "Rosemary56@hotmail.com",
      "password": "SVFqTrx78gOSBKY",
      "restaurant_id": 15
    },
    {
      "name": "Yolanda Marvin",
      "email": "Laurence_Reichert@hotmail.com",
      "password": "wHKqGxDEKlsSfiS",
      "restaurant_id": 4
    },
    {
      "name": "Kaitlin Bartell",
      "email": "Willow_Langworth@gmail.com",
      "password": "lN4au30zefFD5gg",
      "restaurant_id": 11
    },
    {
      "name": "Isaac Bergnaum",
      "email": "Dennis_OKon41@yahoo.com",
      "password": "KkmNkpBQq2OiU1G",
      "restaurant_id": 11
    },
    {
      "name": "Jamaal Klocko",
      "email": "Taryn24@gmail.com",
      "password": "5ztNNnQVHJozUl7",
      "restaurant_id": 10
    },
    {
      "name": "Dudley Wisoky",
      "email": "Clyde_Streich21@gmail.com",
      "password": "ccMgzb6nE_xdNpQ",
      "restaurant_id": 29
    },
    {
      "name": "Mathew McClure",
      "email": "Zola.Klein@yahoo.com",
      "password": "vTlt_8lWW21ZFub",
      "restaurant_id": 11
    },
    {
      "name": "Freeman Pollich",
      "email": "Kay_Yundt@yahoo.com",
      "password": "Qxk4Yi81SJNm52W",
      "restaurant_id": 4
    },
    {
      "name": "Jailyn Beatty",
      "email": "Simeon66@hotmail.com",
      "password": "KnLrmMRW5UOqvUE",
      "restaurant_id": 4
    }
  ]
}
